setup.py
jt_dist20/Binomialdistribution.py
jt_dist20/Gaussiandistribution.py
jt_dist20/Generaldistribution.py
jt_dist20/__init__.py
jt_dist20.egg-info/PKG-INFO
jt_dist20.egg-info/SOURCES.txt
jt_dist20.egg-info/dependency_links.txt
jt_dist20.egg-info/not-zip-safe
jt_dist20.egg-info/top_level.txt