Metadata-Version: 1.0
Name: jt-dist20
Version: 0.1
Summary: Gaussian and binomial distributions
Home-page: UNKNOWN
Author: Jenish Thapa
Author-email: jenisht1@gmail.com
License: UNKNOWN
Platform: UNKNOWN
